litesurf/__init__.py
litesurf/cli.py
litesurf/litesurf.py
litesurf-0.0.2.dist-info/licenses/LICENSE
litesurf-0.0.2.dist-info/METADATA
litesurf-0.0.2.dist-info/WHEEL
litesurf-0.0.2.dist-info/entry_points.txt
litesurf-0.0.2.dist-info/top_level.txt
litesurf-0.0.2.dist-info/RECORD
